masonry/__init__.py
masonry/check.py
masonry/cli.py
masonry/main.py
masonry/postprocess.py
masonry/prompt.py
masonry/render.py
masonry/resolution.py
masonry/template.py
masonry/utils.py
masonry/__pycache__/__init__.cpython-36.pyc
masonry/__pycache__/check.cpython-36.pyc
masonry/__pycache__/cli.cpython-36.pyc
masonry/__pycache__/content.cpython-36.pyc
masonry/__pycache__/feeds.cpython-36.pyc
masonry/__pycache__/haystack.cpython-36.pyc
masonry/__pycache__/initialise_project.cpython-36.pyc
masonry/__pycache__/main.cpython-36.pyc
masonry/__pycache__/nlp.cpython-36.pyc
masonry/__pycache__/postprocess.cpython-36.pyc
masonry/__pycache__/prompt.cpython-36.pyc
masonry/__pycache__/render.cpython-36.pyc
masonry/__pycache__/resolution.cpython-36.pyc
masonry/__pycache__/resolve_deps.cpython-36.pyc
masonry/__pycache__/source_articles.cpython-36.pyc
masonry/__pycache__/source_feeds.cpython-36.pyc
masonry/__pycache__/storage.cpython-36.pyc
masonry/__pycache__/template.cpython-36.pyc
masonry/__pycache__/utils.cpython-36.pyc
masonry-0.1.2.dist-info/DESCRIPTION.rst
masonry-0.1.2.dist-info/METADATA
masonry-0.1.2.dist-info/RECORD
masonry-0.1.2.dist-info/WHEEL
masonry-0.1.2.dist-info/entry_points.txt
masonry-0.1.2.dist-info/metadata.json
masonry-0.1.2.dist-info/top_level.txt
