Metadata-Version: 2.0
Name: masonry
Version: 0.1.2
Summary: A command line tool for composable project templating.
Home-page: https://github.com/MrKriss/masonry
Author: Chris Musselle
Author-email: chris.j.musselle@gmail.com
License: MIT
Platform: UNKNOWN
Classifier: Development Status :: 3 - Alpha
Classifier: License :: OSI Approved :: MIT License
Classifier: Programming Language :: Python :: 3.6
Classifier: Intended Audience :: Developers
Classifier: Intended Audience :: Science/Research
Requires-Dist: clint
Requires-Dist: cookiecutter (>=1.6)
Requires-Dist: docopt
Requires-Dist: gitpython
Requires-Dist: inquirer
Requires-Dist: py
Requires-Dist: ruamel.yaml (>=0.15)
Requires-Dist: schema
